curricula/__init__.py
curricula/__main__.py
curricula/log.py
curricula/models.py
curricula/structure.py
curricula/version.py
curricula/library/__init__.py
curricula/library/callgrind.py
curricula/library/configurable.py
curricula/library/debug.py
curricula/library/files.py
curricula/library/importance.py
curricula/library/inject.py
curricula/library/printer.py
curricula/library/process.py
curricula/library/profile.py
curricula/library/serialization.py
curricula/library/singleton.py
curricula/library/template.py
curricula/library/utility.py
curricula/library/valgrind.py
curricula/shell/__init__.py
curricula/shell/plugin.py
curricula-2.1.2.dist-info/LICENSE
curricula-2.1.2.dist-info/METADATA
curricula-2.1.2.dist-info/WHEEL
curricula-2.1.2.dist-info/top_level.txt
curricula-2.1.2.dist-info/RECORD
