Metadata-Version: 2.1
Name: curricula
Version: 2.1.2
Summary: A content manager and grading toolkit for evaluating student code
Home-page: https://github.com/curriculagg/curricula
Author: Noah Kim
Author-email: noahbkim@gmail.com
License: UNKNOWN
Platform: UNKNOWN
Requires-Python: >=3.9
